amplify_cf/__init__.py
amplify_cf/cli.py
amplify_cf/config.py
amplify_cf/env.py
amplify_cf/ext.py
amplify_cf/schema.py
amplify_cf/utils.py
amplify_cf-0.4.0.dist-info/entry_points.txt
amplify_cf-0.4.0.dist-info/WHEEL
amplify_cf-0.4.0.dist-info/METADATA
amplify_cf-0.4.0.dist-info/RECORD
