Metadata-Version: 2.1
Name: amplify-cf
Version: 0.4.0
Summary: CloudFormation toolkit for amplify.
Keywords: library
Author: Epsy Engineering
Author-email: engineering@epsyhealth.com
Requires-Python: >=3.8,<4.0
Classifier: Programming Language :: Python :: 3
Classifier: Programming Language :: Python :: 3.10
Classifier: Programming Language :: Python :: 3.8
Classifier: Programming Language :: Python :: 3.9
Requires-Dist: PyYAML (>=6.0,<7.0)
Requires-Dist: boto3 (>=1.24.47,<2.0.0)
Requires-Dist: boto3-stubs[cloudformation,essential,appsync] (>=1.24.56,<2.0.0)
Requires-Dist: click (>=8.1.3,<9.0.0)
Requires-Dist: inquirer (>=2.10.0,<3.0.0)
Requires-Dist: python-box (>=6.0.2,<7.0.0)
Requires-Dist: python-dotenv (>=0.20.0,<0.21.0)
